arc_method/__ini__.py
arc_method/core.py
arc_method-0.1.5.dist-info/licenses/LICENSE
arc_method-0.1.5.dist-info/METADATA
arc_method-0.1.5.dist-info/WHEEL
arc_method-0.1.5.dist-info/top_level.txt
arc_method-0.1.5.dist-info/RECORD
