Metadata-Version: 2.4
Name: arc-method
Version: 0.1.5
Summary: Arc Yöntemi tabanlı LLM interaction framework.
Author-email: Arda Akgür <arda@akgur.com>
License: ARC License (Version 1.1)
Project-URL: Homepage, https://arccorp.ai
Project-URL: Source, https://github.com/arcnaboo/arc_method
Project-URL: Issues, https://github.com/arcnaboo/arc_method/issues
Project-URL: Documentation, https://pypi.org/project/arc-method/
Requires-Python: >=3.9
License-File: LICENSE
Requires-Dist: groq>=0.5.0
Requires-Dist: openai>=1.0.0
Dynamic: license-file
